refinitiv/__init__.py
refinitiv/data/__init__.py
refinitiv/data/_base_enum.py
refinitiv/data/_config_defaults.py
refinitiv/data/_configure.py
refinitiv/data/_content_type.py
refinitiv/data/_errors.py
refinitiv/data/_listener.py
refinitiv/data/_log.py
refinitiv/data/_open_state.py
refinitiv/data/_types.py
refinitiv/data/_version.py
refinitiv/data/errors.py
refinitiv/data/warnings.py
refinitiv/data/_access_layer/__init__.py
refinitiv/data/_access_layer/_containers.py
refinitiv/data/_access_layer/_data_df_builder.py
refinitiv/data/_access_layer/_data_provider.py
refinitiv/data/_access_layer/_history_df_builder.py
refinitiv/data/_access_layer/_history_df_builder_factory.py
refinitiv/data/_access_layer/_intervals_consts.py
refinitiv/data/_access_layer/_mixed_streams.py
refinitiv/data/_access_layer/_ohlc_builder.py
refinitiv/data/_access_layer/_pricing_recorder.py
refinitiv/data/_access_layer/_recording_control.py
refinitiv/data/_access_layer/_stream_update_handler.py
refinitiv/data/_access_layer/get_data_func.py
refinitiv/data/_access_layer/get_history_func.py
refinitiv/data/_access_layer/get_stream.py
refinitiv/data/_access_layer/session.py
refinitiv/data/_access_layer/context_collection/__init__.py
refinitiv/data/_access_layer/context_collection/_adc_context.py
refinitiv/data/_access_layer/context_collection/_adc_rdp_context.py
refinitiv/data/_access_layer/context_collection/_adc_udf_context.py
refinitiv/data/_access_layer/context_collection/_context.py
refinitiv/data/_access_layer/context_collection/_context_factory.py
refinitiv/data/_access_layer/context_collection/_cust_inst_context.py
refinitiv/data/_access_layer/context_collection/_cust_inst_rdp_context.py
refinitiv/data/_access_layer/context_collection/_cust_inst_udf_context.py
refinitiv/data/_access_layer/context_collection/_hp_and_cust_inst_context.py
refinitiv/data/_access_layer/context_collection/_hp_context.py
refinitiv/data/_access_layer/dates_and_calendars/__init__.py
refinitiv_data-1.6.2.dist-info/LICENSE
refinitiv_data-1.6.2.dist-info/METADATA
refinitiv_data-1.6.2.dist-info/WHEEL
refinitiv_data-1.6.2.dist-info/top_level.txt
refinitiv_data-1.6.2.dist-info/RECORD
