Metadata-Version: 2.1
Name: refinitiv-data
Version: 1.6.2
Summary: Client for Refinitiv Data Platform API's
Author: REFINITIV
License: Apache 2.0
Project-URL: Homepage, https://developers.refinitiv.com/en/api-catalog/refinitiv-data-platform/refinitiv-data-library-for-python
Project-URL: Documentation, https://developers.refinitiv.com/en/api-catalog/refinitiv-data-platform/refinitiv-data-library-for-python/documentation
Classifier: License :: OSI Approved :: Apache Software License
Classifier: Operating System :: OS Independent
Classifier: Programming Language :: Python :: 3
Classifier: Topic :: Office/Business :: Financial
Requires-Python: >=3.7
License-File: LICENSE
Requires-Dist: appdirs~=1.4.4
Requires-Dist: pyee<=11.1.0,>=9.0.4
Requires-Dist: httpx<0.27.0,>=0.18.0
Requires-Dist: httpcore<1.1.0
Requires-Dist: PyMySQL>=1.0.2
Requires-Dist: numpy~=1.11
Requires-Dist: pandas<3.0.0,>=1.3.5
Requires-Dist: python-dateutil<3.0.0
Requires-Dist: requests~=2.28
Requires-Dist: scipy<1.13.0
Requires-Dist: tenacity~=8.0
Requires-Dist: watchdog<3.0.0,>=0.10.2
Requires-Dist: websocket-client!=1.5.0,!=1.5.2,~=1.5
Requires-Dist: pyhumps<4.0.0,>=3.0.2
Requires-Dist: jinja2<4.0.0,>=3.0.3
Requires-Dist: simplejson~=3.15
